PDStoolkit/PDS_CVA.py
PDStoolkit/PDS_DPCA.py
PDStoolkit/PDS_DPLS.py
PDStoolkit/PDS_PCA.py
PDStoolkit/PDS_PLS.py
PDStoolkit/__init__.py
PDStoolkit-0.0.2.dist-info/LICENSE
PDStoolkit-0.0.2.dist-info/METADATA
PDStoolkit-0.0.2.dist-info/WHEEL
PDStoolkit-0.0.2.dist-info/top_level.txt
PDStoolkit-0.0.2.dist-info/RECORD
