Metadata-Version: 2.1
Name: PDStoolkit
Version: 0.0.2
Summary: A Python package to facilitate building process data science solutions including process modeling, monitoring, fault diagnosis, etc.
Home-page: https://mlforpse.com/intro-to-pdstoolkit-python-package/
Author: Ankur Kumar
Author-email: MLforPSE@gmail.com
Project-URL: Source Code:, https://github.com/ML-PSE/PDStoolkit-Python-Package
Classifier: Programming Language :: Python :: 3
Classifier: License :: OSI Approved :: BSD License
Classifier: Operating System :: OS Independent
Requires-Python: >=3.6
License-File: LICENSE
